signaturelib/__init__.py
signaturelib/services.py
signaturelib/model/__init__.py
signaturelib/model/dao/__init__.py
signaturelib/model/dao/file_dao.py
signaturelib/model/dao/signature_request_dao.py
signaturelib/model/dao/signature_request_user_dao.py
signaturelib/model/dao/user_dao.py
signaturelib/model/dto/__init__.py
signaturelib/model/dto/model_dto.py
signature_lib-1.1.2.dist-info/METADATA
signature_lib-1.1.2.dist-info/WHEEL
signature_lib-1.1.2.dist-info/top_level.txt
signature_lib-1.1.2.dist-info/RECORD
